yasl/__init__.py
yasl/bin/sparkbar.py
yasl/spark.py
yasl-1.0.3.dist-info/entry_points.txt
yasl-1.0.3.dist-info/LICENSE
yasl-1.0.3.dist-info/WHEEL
yasl-1.0.3.dist-info/METADATA
yasl-1.0.3.dist-info/RECORD
